{
    "jsonrpc": "2.0",
    "method": "template.massadd",
    "params": {
        "templates": [
            {
                "templateid": "10085"
            },
            {
                "templateid": "10086"
            }
        ],
        "templates_link": [
            {
                "templateid": "10106"
            },
            {
                "templateid": "10104"
            }
        ],
        "groups": [
            {
                "groupid": "2"
            }
        ]
    },
    "auth": null,
    "id": 1
}